MANIFEST.in
README.rst
setup.py
collective/__init__.py
collective.transform.ppt_xl.egg-info/PKG-INFO
collective.transform.ppt_xl.egg-info/SOURCES.txt
collective.transform.ppt_xl.egg-info/dependency_links.txt
collective.transform.ppt_xl.egg-info/entry_points.txt
collective.transform.ppt_xl.egg-info/namespace_packages.txt
collective.transform.ppt_xl.egg-info/not-zip-safe
collective.transform.ppt_xl.egg-info/requires.txt
collective.transform.ppt_xl.egg-info/top_level.txt
collective/transform/__init__.py
collective/transform/ppt_xl/__init__.py
collective/transform/ppt_xl/configure.zcml
collective/transform/ppt_xl/excel_to_html.py
collective/transform/ppt_xl/ppt_to_html.py
collective/transform/ppt_xl/setuphandlers.py
collective/transform/ppt_xl/tests.py
collective/transform/ppt_xl/version.txt
collective/transform/ppt_xl/profiles/default/collective.transform.xl_ppt.txt
collective/transform/ppt_xl/profiles/default/metadata.xml
docs/HISTORY.txt
docs/INSTALL.txt
docs/LICENSE.txt