Metadata-Version: 1.0
Name: collective.transform.ppt-xl
Version: 0.1
Summary: Powerpoint and Excel to HTML transformation
Home-page: https://github.com/collective/collective.transform.ppt_xl
Author: Christian Ledermann
Author-email: christian.ledermann@gmail.com
License: GPL
Platform: UNKNOWN
Classifier: Framework :: Plone
Classifier: Framework :: Plone :: 4.0
Classifier: Framework :: Plone :: 4.1
Classifier: Programming Language :: Python
Classifier: Operating System :: Unix
Classifier: Topic :: Text Processing
